nb4llm/__init__.py
nb4llm/cli.py
nb4llm/converter.py
nb4llm-0.1.3.dist-info/licenses/LICENSE
nb4llm-0.1.3.dist-info/METADATA
nb4llm-0.1.3.dist-info/WHEEL
nb4llm-0.1.3.dist-info/entry_points.txt
nb4llm-0.1.3.dist-info/top_level.txt
nb4llm-0.1.3.dist-info/RECORD
